main.py
bsor/Bsor.py
bsor/BsorUtil.py
bsor/Bsor_Main.py
bsor/Decoder.py
bsor/EncodeDecodeTest.py
bsor/Encoder.py
bsor/Scoring.py
bsor/__init__.py
py_bsor-1.3.6.dist-info/licenses/LICENSE
test/__init__.py
py_bsor-1.3.6.dist-info/METADATA
py_bsor-1.3.6.dist-info/WHEEL
py_bsor-1.3.6.dist-info/top_level.txt
py_bsor-1.3.6.dist-info/RECORD
