Metadata-Version: 2.4
Name: py-bsor
Version: 1.3.6
Summary: BS Open Replay Parser, with added support for controlleroffsets and userdata/treecksaber
Author-email: Carsten Schipmann <theschippi+gh@gmail.com>
License: MIT License
Project-URL: Homepage, https://github.com/Schippi/py-bsor
Project-URL: Bug Tracker, https://github.com/Schippi/py-bsor/issues
Classifier: Programming Language :: Python :: 3
Classifier: License :: OSI Approved :: MIT License
Classifier: Operating System :: OS Independent
Requires-Python: >=3.7
License-File: LICENSE
Dynamic: license-file
